spotilyzer/__init__.py
spotilyzer/cli.py
spotilyzer/driver.py
spotilyzer/data/seeds.json
spotilyzer/subcommands/__init__.py
spotilyzer/subcommands/base.py
spotilyzer/subcommands/candidates_base.py
spotilyzer/subcommands/create_candidates.py
spotilyzer/subcommands/group_requests.py
spotilyzer/subcommands/init.py
spotilyzer/subcommands/show_candidates.py
spotilyzer/subcommands/size_fleets.py
spotilyzer/subcommands/csv/__init__.py
spotilyzer/subcommands/csv/requests.py
spotilyzer/subcommands/json/__init__.py
spotilyzer/subcommands/json/candidates.py
spotilyzer/subcommands/json/requests.py
spotilyzer/subcommands/json/seeds.py
spotilyzer/subcommands/utils/__init__.py
spotilyzer/subcommands/utils/cli.py
spotilyzer/subcommands/utils/paths.py
spotilyzer/subcommands/utils/stats.py
spotilyzer-0.2.0.dist-info/LICENSE
spotilyzer-0.2.0.dist-info/METADATA
spotilyzer-0.2.0.dist-info/WHEEL
spotilyzer-0.2.0.dist-info/entry_points.txt
spotilyzer-0.2.0.dist-info/top_level.txt
spotilyzer-0.2.0.dist-info/RECORD
