Metadata-Version: 2.1
Name: spotilyzer
Version: 0.2.0
Summary: AWS Spot Fleet Analyzer
Home-page: https://github.com/conrad-mukai/spotilyzer
Author: Conrad Mukai
Author-email: conrad@mukai-home.net
License: MIT
Platform: UNKNOWN
Requires-Dist: jsonschema
Requires-Dist: boto3
Requires-Dist: tabulate
